pyinterceptor/__init__.py
pyinterceptor/exceptions.py
pyinterceptor/core/__init__.py
pyinterceptor/core/_device.py
pyinterceptor/core/_hotkey.py
pyinterceptor/core/_interception.py
pyinterceptor/core/_ioctl.py
pyinterceptor/core/_keyboard.py
pyinterceptor/core/_mouse.py
pyinterceptor/core/_state.py
pyinterceptor/defs/__init__.py
pyinterceptor/defs/_buttons.py
pyinterceptor/defs/_flags.py
pyinterceptor/defs/_keycodes.py
pyinterceptor/defs/_stroke.py
pyinterceptor/utils/decorators.py
pyinterceptor_hotkeys-0.2.0.dist-info/licenses/LICENSE
pyinterceptor_hotkeys-0.2.0.dist-info/METADATA
pyinterceptor_hotkeys-0.2.0.dist-info/WHEEL
pyinterceptor_hotkeys-0.2.0.dist-info/top_level.txt
pyinterceptor_hotkeys-0.2.0.dist-info/RECORD
