Metadata-Version: 2.4
Name: pyinterceptor-hotkeys
Version: 0.2.0
Summary: Python wrapper for Interception driver with hotkey support
Author-email: t4eyoon <utu9201@gmail.com>
License: MIT License
Project-URL: Homepage, https://github.com/t4euyoon/pyinterceptor
Project-URL: Repository, https://github.com/t4euyoon/pyinterceptor
Requires-Python: >=3.7
License-File: LICENSE
Dynamic: license-file
